mkdocs_bootswatch/__init__.py
mkdocs_bootswatch/cerulean/__init__.py
mkdocs_bootswatch/cerulean/mkdocs_theme.yml
mkdocs_bootswatch/cerulean/css/base.css
mkdocs_bootswatch/cerulean/css/bootstrap.min.css
mkdocs_bootswatch/cosmo/__init__.py
mkdocs_bootswatch/cosmo/mkdocs_theme.yml
mkdocs_bootswatch/cosmo/css/base.css
mkdocs_bootswatch/cosmo/css/bootstrap.min.css
mkdocs_bootswatch/cyborg/__init__.py
mkdocs_bootswatch/cyborg/mkdocs_theme.yml
mkdocs_bootswatch/cyborg/css/base.css
mkdocs_bootswatch/cyborg/css/bootstrap.min.css
mkdocs_bootswatch/darkly/__init__.py
mkdocs_bootswatch/darkly/mkdocs_theme.yml
mkdocs_bootswatch/darkly/css/base.css
mkdocs_bootswatch/darkly/css/bootstrap.min.css
mkdocs_bootswatch/flatly/__init__.py
mkdocs_bootswatch/flatly/mkdocs_theme.yml
mkdocs_bootswatch/flatly/css/base.css
mkdocs_bootswatch/flatly/css/bootstrap.min.css
mkdocs_bootswatch/journal/__init__.py
mkdocs_bootswatch/journal/mkdocs_theme.yml
mkdocs_bootswatch/journal/css/base.css
mkdocs_bootswatch/journal/css/bootstrap.min.css
mkdocs_bootswatch/litera/__init__.py
mkdocs_bootswatch/litera/mkdocs_theme.yml
mkdocs_bootswatch/litera/css/base.css
mkdocs_bootswatch/litera/css/bootstrap.min.css
mkdocs_bootswatch/lumen/__init__.py
mkdocs_bootswatch/lumen/mkdocs_theme.yml
mkdocs_bootswatch/lumen/css/base.css
mkdocs_bootswatch/lumen/css/bootstrap.min.css
mkdocs_bootswatch/lux/__init__.py
mkdocs_bootswatch/lux/mkdocs_theme.yml
mkdocs_bootswatch/lux/css/base.css
mkdocs_bootswatch/lux/css/bootstrap.min.css
mkdocs_bootswatch/materia/__init__.py
mkdocs_bootswatch/materia/mkdocs_theme.yml
mkdocs_bootswatch/materia/css/base.css
mkdocs_bootswatch/materia/css/bootstrap.min.css
mkdocs_bootswatch/minty/__init__.py
mkdocs_bootswatch/minty/mkdocs_theme.yml
mkdocs_bootswatch/minty/css/base.css
mkdocs_bootswatch/minty/css/bootstrap.min.css
mkdocs_bootswatch/pulse/__init__.py
mkdocs_bootswatch/pulse/mkdocs_theme.yml
mkdocs_bootswatch/pulse/css/base.css
mkdocs_bootswatch/pulse/css/bootstrap.min.css
mkdocs_bootswatch-1.1.dist-info/LICENSE
mkdocs_bootswatch-1.1.dist-info/METADATA
mkdocs_bootswatch-1.1.dist-info/WHEEL
mkdocs_bootswatch-1.1.dist-info/entry_points.txt
mkdocs_bootswatch-1.1.dist-info/top_level.txt
mkdocs_bootswatch-1.1.dist-info/RECORD
